cassummaryparser/CasParser.py
cassummaryparser/CasRecord.py
cassummaryparser/__init__.py
cassummaryparser-0.1.4.dist-info/METADATA
cassummaryparser-0.1.4.dist-info/WHEEL
cassummaryparser-0.1.4.dist-info/top_level.txt
cassummaryparser-0.1.4.dist-info/RECORD
