Metadata-Version: 2.1
Name: cassummaryparser
Version: 0.1.4
Summary: Cas summary parser
Author: Nethish Rajendran
Author-email: nethish259@gmail.com
Requires-Dist: tabula-py ==2.9.0
Requires-Dist: jpype1 ==1.5.0
